bibin.py
bibin-0.2.1.dist-info/METADATA
bibin-0.2.1.dist-info/WHEEL
bibin-0.2.1.dist-info/entry_points.txt
bibin-0.2.1.dist-info/licenses/COPYING.WTFPL
bibin-0.2.1.dist-info/RECORD
