Metadata-Version: 2.4
Name: bibin
Version: 0.2.1
Summary: bibin - trash files and folders
Project-URL: Homepage, https://gitlab.com/hydrargyrum/bibin
License-Expression: WTFPL
License-File: COPYING.WTFPL
Keywords: delete,files,freedesktop,remove,trash
Classifier: Development Status :: 4 - Beta
Classifier: Intended Audience :: Developers
Classifier: License :: Public Domain
Classifier: Programming Language :: Python :: 3
Classifier: Programming Language :: Python :: 3.7
Classifier: Programming Language :: Python :: 3.8
Classifier: Programming Language :: Python :: 3.9
Classifier: Programming Language :: Python :: 3.10
Classifier: Programming Language :: Python :: 3.11
Classifier: Programming Language :: Python :: 3.12
Classifier: Programming Language :: Python :: 3.13
Classifier: Topic :: Software Development :: Libraries :: Python Modules
Classifier: Topic :: System :: Filesystems
Classifier: Topic :: Utilities
Requires-Python: >=3
